zertoapl/__init__.py
zertoapl/vpg.py
zertoapl/vra.py
zertoapl/zerto_auth.py
zertoapl/zvm.py
zertoapilib-0.0.1.dist-info/LICENSE
zertoapilib-0.0.1.dist-info/METADATA
zertoapilib-0.0.1.dist-info/WHEEL
zertoapilib-0.0.1.dist-info/top_level.txt
zertoapilib-0.0.1.dist-info/RECORD
